obshell/__init__.py
obshell/arch.py
obshell/client.py
obshell/info.py
obshell/log.py
obshell/mirror.py
obshell/package.py
obshell/pkg.py
obshell/request.py
obshell/ssh.py
obshell/auth/__init__.py
obshell/auth/base.py
obshell/auth/password.py
obshell/model/__init__.py
obshell/model/database.py
obshell/model/format.py
obshell/model/info.py
obshell/model/ob.py
obshell/model/recyclebin.py
obshell/model/resource_pool.py
obshell/model/task.py
obshell/model/tenant.py
obshell/model/unit.py
obshell/model/user.py
obshell/model/version.py
obshell/service/__init__.py
obshell/service/client_set.py
obshell/service/client_v1.py
obshell-0.0.7.dist-info/licenses/LICENSE
obshell-0.0.7.dist-info/licenses/NOTICE
obshell-0.0.7.dist-info/METADATA
obshell-0.0.7.dist-info/WHEEL
obshell-0.0.7.dist-info/top_level.txt
obshell-0.0.7.dist-info/RECORD
