Metadata-Version: 2.4
Name: obshell
Version: 0.0.7
Summary: OBShell SDK is a powerful and easy-to-use Python library that provides developers with simple method calls to interact with the OBShell. OBShell SDK allows for quick integration, enabling developers to efficiently implement features and focus on creating value in their applications.
Home-page: https://github.com/oceanbase/obshell-sdk-python
Author: OceanBase
Author-email: rongfeng.frf@oceanbase.com
License: Apache-2.0
Classifier: Development Status :: 3 - Alpha
Classifier: Programming Language :: Python :: 3
Classifier: License :: OSI Approved :: Apache Software License
Requires-Python: >=3.6
License-File: LICENSE
License-File: NOTICE
Requires-Dist: pycryptodome
Requires-Dist: requests
Requires-Dist: rpmfile
Requires-Dist: paramiko
Dynamic: author
Dynamic: author-email
Dynamic: classifier
Dynamic: description
Dynamic: description-content-type
Dynamic: home-page
Dynamic: license
Dynamic: license-file
Dynamic: requires-dist
Dynamic: requires-python
Dynamic: summary
